[
  {
    "product_id": "123",
    "parsed_options": [
      {
        "id": 140,
        "group": "Turnaround",
        "name": "2 - 3 Business Days",
        "hidden": 0
      },
      {
        "id": 141,
        "group": "qty",
        "name": "10",
        "hidden": 0
      },
      {
        "id": 273,
        "group": "qty",
        "name": "1",
        "hidden": 0
      },
      {
        "id": 274,
        "group": "qty",
        "name": "2",
        "hidden": 0
      },
      {
        "id": 275,
        "group": "qty",
        "name": "3",
        "hidden": 0
      },
      {
        "id": 276,
        "group": "qty",
        "name": "4",
        "hidden": 0
      },
      {
        "id": 277,
        "group": "qty",
        "name": "5",
        "hidden": 0
      },
      {
        "id": 278,
        "group": "qty",
        "name": "6",
        "hidden": 0
      },
      {
        "id": 279,
        "group": "qty",
        "name": "7",
        "hidden": 0
      },
      {
        "id": 280,
        "group": "qty",
        "name": "8",
        "hidden": 0
      },
      {
        "id": 281,
        "group": "qty",
        "name": "9",
        "hidden": 0
      },
      {
        "id": 452,
        "group": "Product",
        "name": "Profit Pak",
        "hidden": 0
      },
      {
        "id": 453,
        "group": "size",
        "name": "Swatch Book + Large Format Samples",
        "hidden": 0
      }
    ]
  }
]