[
  {
    "product_id": "105",
    "parsed_options": [
      {
        "id": 18,
        "group": "Turnaround",
        "name": "4 - 5 Business Days",
        "hidden": 0
      },
      {
        "id": 141,
        "group": "qty",
        "name": "10",
        "hidden": 0
      },
      {
        "id": 219,
        "group": "size",
        "name": "24 x 36",
        "hidden": 0
      },
      {
        "id": 262,
        "group": "size",
        "name": "12 x 24",
        "hidden": 0
      },
      {
        "id": 263,
        "group": "size",
        "name": "12 x 36",
        "hidden": 0
      },
      {
        "id": 264,
        "group": "size",
        "name": "12 x 48",
        "hidden": 0
      },
      {
        "id": 265,
        "group": "size",
        "name": "24 x 24",
        "hidden": 0
      },
      {
        "id": 267,
        "group": "size",
        "name": "24 x 48",
        "hidden": 0
      },
      {
        "id": 270,
        "group": "size",
        "name": "36 x 36",
        "hidden": 0
      },
      {
        "id": 271,
        "group": "size",
        "name": "36 x 48",
        "hidden": 0
      },
      {
        "id": 272,
        "group": "size",
        "name": "48 x 48",
        "hidden": 0
      },
      {
        "id": 273,
        "group": "qty",
        "name": "1",
        "hidden": 0
      },
      {
        "id": 274,
        "group": "qty",
        "name": "2",
        "hidden": 0
      },
      {
        "id": 275,
        "group": "qty",
        "name": "3",
        "hidden": 0
      },
      {
        "id": 276,
        "group": "qty",
        "name": "4",
        "hidden": 0
      },
      {
        "id": 277,
        "group": "qty",
        "name": "5",
        "hidden": 0
      },
      {
        "id": 278,
        "group": "qty",
        "name": "6",
        "hidden": 0
      },
      {
        "id": 279,
        "group": "qty",
        "name": "7",
        "hidden": 0
      },
      {
        "id": 280,
        "group": "qty",
        "name": "8",
        "hidden": 0
      },
      {
        "id": 281,
        "group": "qty",
        "name": "9",
        "hidden": 0
      },
      {
        "id": 325,
        "group": "size",
        "name": "12 x 60",
        "hidden": 0
      },
      {
        "id": 326,
        "group": "size",
        "name": "24 x 60",
        "hidden": 0
      },
      {
        "id": 334,
        "group": "size",
        "name": "36 x 60",
        "hidden": 0
      },
      {
        "id": 342,
        "group": "size",
        "name": "48 x 60",
        "hidden": 0
      },
      {
        "id": 344,
        "group": "size",
        "name": "72 x 12",
        "hidden": 0
      },
      {
        "id": 345,
        "group": "size",
        "name": "72 x 24",
        "hidden": 0
      },
      {
        "id": 346,
        "group": "size",
        "name": "72 x 36",
        "hidden": 0
      },
      {
        "id": 347,
        "group": "size",
        "name": "72 x 48",
        "hidden": 0
      },
      {
        "id": 349,
        "group": "size",
        "name": "84 x 12",
        "hidden": 0
      },
      {
        "id": 350,
        "group": "size",
        "name": "84 x 24",
        "hidden": 0
      },
      {
        "id": 351,
        "group": "size",
        "name": "84 x 36",
        "hidden": 0
      },
      {
        "id": 352,
        "group": "size",
        "name": "84 x 48",
        "hidden": 0
      },
      {
        "id": 354,
        "group": "size",
        "name": "96 x 12",
        "hidden": 0
      },
      {
        "id": 355,
        "group": "size",
        "name": "96 x 24",
        "hidden": 0
      },
      {
        "id": 356,
        "group": "size",
        "name": "96 x 36",
        "hidden": 0
      },
      {
        "id": 357,
        "group": "size",
        "name": "96 x 48",
        "hidden": 0
      },
      {
        "id": 386,
        "group": "Stock",
        "name": "8pt C2S Printed 1 Sided (4/0)",
        "hidden": 0
      },
      {
        "id": 387,
        "group": "size",
        "name": "16 x 20",
        "hidden": 0
      },
      {
        "id": 388,
        "group": "size",
        "name": "20 x 24",
        "hidden": 0
      },
      {
        "id": 389,
        "group": "size",
        "name": "22 x 28",
        "hidden": 0
      }
    ]
  },
  {
    "product_id": "65",
    "parsed_options": [
      {
        "id": 5,
        "group": "qty",
        "name": "50",
        "hidden": 0
      },
      {
        "id": 6,
        "group": "qty",
        "name": "75",
        "hidden": 0
      },
      {
        "id": 7,
        "group": "qty",
        "name": "100",
        "hidden": 0
      },
      {
        "id": 9,
        "group": "qty",
        "name": "250",
        "hidden": 0
      },
      {
        "id": 12,
        "group": "qty",
        "name": "500",
        "hidden": 0
      },
      {
        "id": 13,
        "group": "qty",
        "name": "750",
        "hidden": 0
      },
      {
        "id": 14,
        "group": "qty",
        "name": "1000",
        "hidden": 0
      },
      {
        "id": 18,
        "group": "Turnaround",
        "name": "4 - 5 Business Days",
        "hidden": 0
      },
      {
        "id": 22,
        "group": "qty",
        "name": "2500",
        "hidden": 0
      },
      {
        "id": 23,
        "group": "qty",
        "name": "5000",
        "hidden": 0
      },
      {
        "id": 25,
        "group": "qty",
        "name": "10000",
        "hidden": 0
      },
      {
        "id": 60,
        "group": "qty",
        "name": "15000",
        "hidden": 0
      },
      {
        "id": 61,
        "group": "qty",
        "name": "20000",
        "hidden": 0
      },
      {
        "id": 62,
        "group": "qty",
        "name": "25000",
        "hidden": 0
      },
      {
        "id": 63,
        "group": "qty",
        "name": "30000",
        "hidden": 0
      },
      {
        "id": 64,
        "group": "qty",
        "name": "35000",
        "hidden": 0
      },
      {
        "id": 65,
        "group": "qty",
        "name": "40000",
        "hidden": 0
      },
      {
        "id": 66,
        "group": "qty",
        "name": "45000",
        "hidden": 0
      },
      {
        "id": 67,
        "group": "qty",
        "name": "50000",
        "hidden": 0
      },
      {
        "id": 68,
        "group": "qty",
        "name": "55000",
        "hidden": 0
      },
      {
        "id": 69,
        "group": "qty",
        "name": "60000",
        "hidden": 0
      },
      {
        "id": 70,
        "group": "qty",
        "name": "65000",
        "hidden": 0
      },
      {
        "id": 71,
        "group": "qty",
        "name": "70000",
        "hidden": 0
      },
      {
        "id": 72,
        "group": "qty",
        "name": "75000",
        "hidden": 0
      },
      {
        "id": 73,
        "group": "qty",
        "name": "80000",
        "hidden": 0
      },
      {
        "id": 74,
        "group": "qty",
        "name": "85000",
        "hidden": 0
      },
      {
        "id": 75,
        "group": "qty",
        "name": "90000",
        "hidden": 0
      },
      {
        "id": 76,
        "group": "qty",
        "name": "95000",
        "hidden": 0
      },
      {
        "id": 77,
        "group": "qty",
        "name": "100000",
        "hidden": 0
      },
      {
        "id": 91,
        "group": "Stock",
        "name": "100LB Gloss Text Printed 1 Side (4/0)",
        "hidden": 0
      },
      {
        "id": 92,
        "group": "Stock",
        "name": "100LB Gloss Text Printed 2 Sides (4/4)",
        "hidden": 0
      },
      {
        "id": 93,
        "group": "Coating",
        "name": "No Coating",
        "hidden": 0
      },
      {
        "id": 102,
        "group": "size",
        "name": "12 x 18",
        "hidden": 0
      },
      {
        "id": 105,
        "group": "qty",
        "name": "25",
        "hidden": 0
      },
      {
        "id": 217,
        "group": "size",
        "name": "18 x 24",
        "hidden": 0
      },
      {
        "id": 218,
        "group": "size",
        "name": "19 x 27",
        "hidden": 0
      },
      {
        "id": 219,
        "group": "size",
        "name": "24 x 36",
        "hidden": 0
      }
    ]
  },
  {
    "product_id": "66",
    "parsed_options": [
      {
        "id": 5,
        "group": "qty",
        "name": "50",
        "hidden": 0
      },
      {
        "id": 6,
        "group": "qty",
        "name": "75",
        "hidden": 0
      },
      {
        "id": 7,
        "group": "qty",
        "name": "100",
        "hidden": 0
      },
      {
        "id": 9,
        "group": "qty",
        "name": "250",
        "hidden": 0
      },
      {
        "id": 12,
        "group": "qty",
        "name": "500",
        "hidden": 0
      },
      {
        "id": 13,
        "group": "qty",
        "name": "750",
        "hidden": 0
      },
      {
        "id": 14,
        "group": "qty",
        "name": "1000",
        "hidden": 0
      },
      {
        "id": 18,
        "group": "Turnaround",
        "name": "4 - 5 Business Days",
        "hidden": 0
      },
      {
        "id": 22,
        "group": "qty",
        "name": "2500",
        "hidden": 0
      },
      {
        "id": 23,
        "group": "qty",
        "name": "5000",
        "hidden": 0
      },
      {
        "id": 25,
        "group": "qty",
        "name": "10000",
        "hidden": 0
      },
      {
        "id": 32,
        "group": "Coating",
        "name": "Matte Finish",
        "hidden": 0
      },
      {
        "id": 60,
        "group": "qty",
        "name": "15000",
        "hidden": 0
      },
      {
        "id": 61,
        "group": "qty",
        "name": "20000",
        "hidden": 0
      },
      {
        "id": 62,
        "group": "qty",
        "name": "25000",
        "hidden": 0
      },
      {
        "id": 63,
        "group": "qty",
        "name": "30000",
        "hidden": 0
      },
      {
        "id": 64,
        "group": "qty",
        "name": "35000",
        "hidden": 0
      },
      {
        "id": 65,
        "group": "qty",
        "name": "40000",
        "hidden": 0
      },
      {
        "id": 66,
        "group": "qty",
        "name": "45000",
        "hidden": 0
      },
      {
        "id": 67,
        "group": "qty",
        "name": "50000",
        "hidden": 0
      },
      {
        "id": 68,
        "group": "qty",
        "name": "55000",
        "hidden": 0
      },
      {
        "id": 69,
        "group": "qty",
        "name": "60000",
        "hidden": 0
      },
      {
        "id": 70,
        "group": "qty",
        "name": "65000",
        "hidden": 0
      },
      {
        "id": 71,
        "group": "qty",
        "name": "70000",
        "hidden": 0
      },
      {
        "id": 72,
        "group": "qty",
        "name": "75000",
        "hidden": 0
      },
      {
        "id": 73,
        "group": "qty",
        "name": "80000",
        "hidden": 0
      },
      {
        "id": 74,
        "group": "qty",
        "name": "85000",
        "hidden": 0
      },
      {
        "id": 75,
        "group": "qty",
        "name": "90000",
        "hidden": 0
      },
      {
        "id": 76,
        "group": "qty",
        "name": "95000",
        "hidden": 0
      },
      {
        "id": 77,
        "group": "qty",
        "name": "100000",
        "hidden": 0
      },
      {
        "id": 91,
        "group": "Stock",
        "name": "100LB Gloss Text Printed 1 Side (4/0)",
        "hidden": 0
      },
      {
        "id": 92,
        "group": "Stock",
        "name": "100LB Gloss Text Printed 2 Sides (4/4)",
        "hidden": 0
      },
      {
        "id": 102,
        "group": "size",
        "name": "12 x 18",
        "hidden": 0
      },
      {
        "id": 105,
        "group": "qty",
        "name": "25",
        "hidden": 0
      },
      {
        "id": 217,
        "group": "size",
        "name": "18 x 24",
        "hidden": 0
      },
      {
        "id": 218,
        "group": "size",
        "name": "19 x 27",
        "hidden": 0
      },
      {
        "id": 219,
        "group": "size",
        "name": "24 x 36",
        "hidden": 0
      }
    ]
  },
  {
    "product_id": "67",
    "parsed_options": [
      {
        "id": 5,
        "group": "qty",
        "name": "50",
        "hidden": 0
      },
      {
        "id": 6,
        "group": "qty",
        "name": "75",
        "hidden": 0
      },
      {
        "id": 7,
        "group": "qty",
        "name": "100",
        "hidden": 0
      },
      {
        "id": 9,
        "group": "qty",
        "name": "250",
        "hidden": 0
      },
      {
        "id": 12,
        "group": "qty",
        "name": "500",
        "hidden": 0
      },
      {
        "id": 13,
        "group": "qty",
        "name": "750",
        "hidden": 0
      },
      {
        "id": 14,
        "group": "qty",
        "name": "1000",
        "hidden": 0
      },
      {
        "id": 18,
        "group": "Turnaround",
        "name": "4 - 5 Business Days",
        "hidden": 0
      },
      {
        "id": 22,
        "group": "qty",
        "name": "2500",
        "hidden": 0
      },
      {
        "id": 23,
        "group": "qty",
        "name": "5000",
        "hidden": 0
      },
      {
        "id": 25,
        "group": "qty",
        "name": "10000",
        "hidden": 0
      },
      {
        "id": 60,
        "group": "qty",
        "name": "15000",
        "hidden": 0
      },
      {
        "id": 61,
        "group": "qty",
        "name": "20000",
        "hidden": 0
      },
      {
        "id": 62,
        "group": "qty",
        "name": "25000",
        "hidden": 0
      },
      {
        "id": 63,
        "group": "qty",
        "name": "30000",
        "hidden": 0
      },
      {
        "id": 64,
        "group": "qty",
        "name": "35000",
        "hidden": 0
      },
      {
        "id": 65,
        "group": "qty",
        "name": "40000",
        "hidden": 0
      },
      {
        "id": 66,
        "group": "qty",
        "name": "45000",
        "hidden": 0
      },
      {
        "id": 67,
        "group": "qty",
        "name": "50000",
        "hidden": 0
      },
      {
        "id": 68,
        "group": "qty",
        "name": "55000",
        "hidden": 0
      },
      {
        "id": 69,
        "group": "qty",
        "name": "60000",
        "hidden": 0
      },
      {
        "id": 70,
        "group": "qty",
        "name": "65000",
        "hidden": 0
      },
      {
        "id": 71,
        "group": "qty",
        "name": "70000",
        "hidden": 0
      },
      {
        "id": 72,
        "group": "qty",
        "name": "75000",
        "hidden": 0
      },
      {
        "id": 73,
        "group": "qty",
        "name": "80000",
        "hidden": 0
      },
      {
        "id": 74,
        "group": "qty",
        "name": "85000",
        "hidden": 0
      },
      {
        "id": 75,
        "group": "qty",
        "name": "90000",
        "hidden": 0
      },
      {
        "id": 76,
        "group": "qty",
        "name": "95000",
        "hidden": 0
      },
      {
        "id": 77,
        "group": "qty",
        "name": "100000",
        "hidden": 0
      },
      {
        "id": 91,
        "group": "Stock",
        "name": "100LB Gloss Text Printed 1 Side (4/0)",
        "hidden": 0
      },
      {
        "id": 92,
        "group": "Stock",
        "name": "100LB Gloss Text Printed 2 Sides (4/4)",
        "hidden": 0
      },
      {
        "id": 102,
        "group": "size",
        "name": "12 x 18",
        "hidden": 0
      },
      {
        "id": 105,
        "group": "qty",
        "name": "25",
        "hidden": 0
      },
      {
        "id": 107,
        "group": "Coating",
        "name": "UV",
        "hidden": 0
      },
      {
        "id": 217,
        "group": "size",
        "name": "18 x 24",
        "hidden": 0
      },
      {
        "id": 218,
        "group": "size",
        "name": "19 x 27",
        "hidden": 0
      },
      {
        "id": 219,
        "group": "size",
        "name": "24 x 36",
        "hidden": 0
      }
    ]
  },
  {
    "product_id": "68",
    "parsed_options": [
      {
        "id": 3,
        "group": "Coating",
        "name": "Uncoated",
        "hidden": 0
      },
      {
        "id": 5,
        "group": "qty",
        "name": "50",
        "hidden": 0
      },
      {
        "id": 6,
        "group": "qty",
        "name": "75",
        "hidden": 0
      },
      {
        "id": 7,
        "group": "qty",
        "name": "100",
        "hidden": 0
      },
      {
        "id": 9,
        "group": "qty",
        "name": "250",
        "hidden": 0
      },
      {
        "id": 12,
        "group": "qty",
        "name": "500",
        "hidden": 0
      },
      {
        "id": 13,
        "group": "qty",
        "name": "750",
        "hidden": 0
      },
      {
        "id": 14,
        "group": "qty",
        "name": "1000",
        "hidden": 0
      },
      {
        "id": 18,
        "group": "Turnaround",
        "name": "4 - 5 Business Days",
        "hidden": 0
      },
      {
        "id": 22,
        "group": "qty",
        "name": "2500",
        "hidden": 0
      },
      {
        "id": 23,
        "group": "qty",
        "name": "5000",
        "hidden": 0
      },
      {
        "id": 25,
        "group": "qty",
        "name": "10000",
        "hidden": 0
      },
      {
        "id": 60,
        "group": "qty",
        "name": "15000",
        "hidden": 0
      },
      {
        "id": 61,
        "group": "qty",
        "name": "20000",
        "hidden": 0
      },
      {
        "id": 62,
        "group": "qty",
        "name": "25000",
        "hidden": 0
      },
      {
        "id": 63,
        "group": "qty",
        "name": "30000",
        "hidden": 0
      },
      {
        "id": 64,
        "group": "qty",
        "name": "35000",
        "hidden": 0
      },
      {
        "id": 65,
        "group": "qty",
        "name": "40000",
        "hidden": 0
      },
      {
        "id": 66,
        "group": "qty",
        "name": "45000",
        "hidden": 0
      },
      {
        "id": 67,
        "group": "qty",
        "name": "50000",
        "hidden": 0
      },
      {
        "id": 68,
        "group": "qty",
        "name": "55000",
        "hidden": 0
      },
      {
        "id": 69,
        "group": "qty",
        "name": "60000",
        "hidden": 0
      },
      {
        "id": 70,
        "group": "qty",
        "name": "65000",
        "hidden": 0
      },
      {
        "id": 71,
        "group": "qty",
        "name": "70000",
        "hidden": 0
      },
      {
        "id": 72,
        "group": "qty",
        "name": "75000",
        "hidden": 0
      },
      {
        "id": 73,
        "group": "qty",
        "name": "80000",
        "hidden": 0
      },
      {
        "id": 74,
        "group": "qty",
        "name": "85000",
        "hidden": 0
      },
      {
        "id": 75,
        "group": "qty",
        "name": "90000",
        "hidden": 0
      },
      {
        "id": 76,
        "group": "qty",
        "name": "95000",
        "hidden": 0
      },
      {
        "id": 77,
        "group": "qty",
        "name": "100000",
        "hidden": 0
      },
      {
        "id": 102,
        "group": "size",
        "name": "12 x 18",
        "hidden": 0
      },
      {
        "id": 105,
        "group": "qty",
        "name": "25",
        "hidden": 0
      },
      {
        "id": 109,
        "group": "Stock",
        "name": "80LB Enviro Printed 1 Side (4/0)",
        "hidden": 0
      },
      {
        "id": 110,
        "group": "Stock",
        "name": "80LB Enviro Printed 2 Sides (4/4)",
        "hidden": 0
      },
      {
        "id": 217,
        "group": "size",
        "name": "18 x 24",
        "hidden": 0
      },
      {
        "id": 218,
        "group": "size",
        "name": "19 x 27",
        "hidden": 0
      },
      {
        "id": 219,
        "group": "size",
        "name": "24 x 36",
        "hidden": 0
      }
    ]
  }
]